pyascvd-0.1.0.dist-info/METADATA
pyascvd-0.1.0.dist-info/WHEEL
pyascvd-0.1.0.dist-info/license_files/LICENSE.txt
maturin/__init__.py
maturin/maturin.cpython-311-x86_64-linux-gnu.so
pyascvd-0.1.0.dist-info/RECORD
