Metadata-Version: 2.1
Name: pyascvd
Version: 0.1.0
Classifier: Programming Language :: Rust
Classifier: Programming Language :: Python :: Implementation :: CPython
Classifier: Programming Language :: Python :: Implementation :: PyPy
License-File: LICENSE.txt
Summary: Python implementation of 2013 ACC ASCVD Risk Estimator Plus Equation
Author-email: lhegstrom@nference.net
Requires-Python: >=3.7
Project-URL: Source, https://github.com/lhegstrom/PyASCVD/
Project-URL: Tracker, https://github.com/lhegstrom/PyASCVD/issues
